allennlp_hydra/__init__.py
allennlp_hydra/version.py
allennlp_hydra/commands/__init__.py
allennlp_hydra/commands/class_to_yaml.py
allennlp_hydra/commands/compose_config.py
allennlp_hydra/commands/hydra_train.py
allennlp_hydra/config/__init__.py
allennlp_hydra/config/fill_defaults.py
allennlp_hydra/utils/__init__.py
allennlp_hydra/utils/testing/__init__.py
allennlp_hydra/utils/testing/test_case.py
allennlp_hydra/utils/testing/utils.py
allennlp_hydra-0.0.7.dist-info/LICENSE
allennlp_hydra-0.0.7.dist-info/METADATA
allennlp_hydra-0.0.7.dist-info/WHEEL
allennlp_hydra-0.0.7.dist-info/top_level.txt
allennlp_hydra-0.0.7.dist-info/RECORD
