Metadata-Version: 2.1
Name: allennlp-hydra
Version: 0.0.7
Summary: Hydra plugin for allennlp
Home-page: UNKNOWN
Author: Gabriel Orlanski
Author-email: gabeorlanski@gmail.com
License: Apache 2.0
Project-URL: Documentation, https://github.com/gabeorlanski/allennlp-hydra
Project-URL: Source Code, https://github.com/gabeorlanski/allennlp-hydra
Platform: UNKNOWN
Classifier: Intended Audience :: Science/Research
Classifier: Development Status :: 3 - Alpha
Classifier: License :: OSI Approved :: Apache Software License
Classifier: Programming Language :: Python :: 3
Classifier: Topic :: Scientific/Engineering :: Artificial Intelligence
License-File: LICENSE
Requires-Dist: allennlp (>=2.6.0)
Requires-Dist: hydra-core (>=1.1.1)
Requires-Dist: overrides (>=3.1.0)
Requires-Dist: omegaconf (>=2.1)
